milkpay/cryptomus/__init__.py
milkpay/cryptomus/__meta__.py
milkpay/cryptomus/py.typed
milkpay/cryptomus/business/__init__.py
milkpay/cryptomus/business/client.py
milkpay/cryptomus/business/exceptions.py
milkpay/cryptomus/business/headers.py
milkpay/cryptomus/business/enums/__init__.py
milkpay/cryptomus/business/enums/currency.py
milkpay/cryptomus/business/enums/exchange_rate_source.py
milkpay/cryptomus/business/enums/invoice_status.py
milkpay/cryptomus/business/enums/invoice_type.py
milkpay/cryptomus/business/enums/network.py
milkpay/cryptomus/business/enums/payout_priority_type.py
milkpay/cryptomus/business/enums/payout_status.py
milkpay/cryptomus/business/enums/recurring_payment_period.py
milkpay/cryptomus/business/enums/recurring_payment_status.py
milkpay/cryptomus/business/enums/static_wallet_status.py
milkpay/cryptomus/business/methods/__init__.py
milkpay/cryptomus/business/methods/base.py
milkpay/cryptomus/business/methods/block_wallet.py
milkpay/cryptomus/business/methods/cancel_recurring_payment.py
milkpay/cryptomus/business/methods/create_invoice.py
milkpay/cryptomus/business/methods/create_payout.py
milkpay/cryptomus/business/methods/create_recurring_payment.py
milkpay/cryptomus/business/methods/create_wallet.py
milkpay/cryptomus/business/methods/generate_wallet_qr.py
milkpay/cryptomus/business/methods/get_balance.py
milkpay/cryptomus/business/methods/get_discount_list.py
milkpay/cryptomus/business/methods/get_exchange_rates.py
milkpay/cryptomus/business/methods/get_payment_history.py
milkpay/cryptomus/business/methods/get_payment_info.py
milkpay/cryptomus/business/methods/get_payment_services.py
milkpay/cryptomus/business/methods/get_payout_history.py
milkpay/cryptomus/business/methods/get_payout_info.py
milkpay/cryptomus/business/methods/get_payout_services.py
milkpay/cryptomus/business/methods/get_recurring_payment_info.py
milkpay/cryptomus/business/methods/get_recurring_payments.py
milkpay/cryptomus/business/methods/refund.py
milkpay_cryptomus-1.2.0.dist-info/METADATA
milkpay_cryptomus-1.2.0.dist-info/WHEEL
milkpay_cryptomus-1.2.0.dist-info/licenses/LICENSE
milkpay_cryptomus-1.2.0.dist-info/RECORD
